{
    "@class": "com.kony.gen.skin.model.KVizSkin",
    "applicableblockedUIWidget": "Button",
    "background_color": "ededed00",
    "bg_type": "one",
    "border_color": "42424200",
    "border_style": "plain",
    "border_type": 0,
    "border_width": 0,
    "bottom_left_border_color": "00000000",
    "bottom_left_border_radius": 10,
    "bottom_left_border_width": 0,
    "bottom_right_border_color": "00000000",
    "bottom_right_border_radius": 10,
    "bottom_right_border_width": 0,
    "delinkedPltfrms": {
        "desktop": [],
        "mobile": [
            "iphone"
        ],
        "tablet": []
    },
    "font_color": "7e7e7e00",
    "font_name": "",
    "font_size": 180,
    "font_style": "normal",
    "font_weight": "normal",
    "gridLineColor": "0000000",
    "isDefaultSkin": false,
    "isForked": false,
    "kuid": "scd007a166304f5e84d6a149b7dbe0a4",
    "platforms": {
        "android": {
            "@class": "com.kony.gen.skin.model.KVizAndroidSkin",
            "font_name": "default",
            "wType": "Label"
        },
        "desktopweb": {
            "@class": "com.kony.gen.skin.model.KVizDesktopWebSkin",
            "background_color": "ffffffff",
            "bg_type": "one",
            "bottom_left_border_color": "42424200",
            "bottom_left_border_style": "plain",
            "bottom_left_border_width": 0,
            "bottom_right_border_color": "42424200",
            "bottom_right_border_style": "plain",
            "bottom_right_border_width": 0,
            "font_color": "398dcf00",
            "font_name": "Andale Mono",
            "font_size": 170,
            "isForked": true,
            "text_shadow": {
                "br": 0,
                "color": "000000",
                "nm": 0,
                "x": 0,
                "y": 0
            },
            "top_left_border_color": "42424200",
            "top_left_border_style": "plain",
            "top_left_border_width": 0,
            "top_right_border_color": "42424200",
            "top_right_border_style": "plain",
            "top_right_border_width": 0,
            "wType": "Label"
        },
        "ipad": {
            "@class": "com.kony.gen.skin.model.KVizIPadSkin",
            "background_color": "ffffffff",
            "bg_type": "one",
            "font_color": "398dcf00",
            "font_name": "AmericanTypewriter",
            "font_size": 170,
            "isForked": true,
            "text_shadow": {
                "br": 0,
                "color": "000000",
                "nm": 0,
                "x": 0,
                "y": 0
            },
            "wType": "Label"
        },
        "iphone": {
            "@class": "com.kony.gen.skin.model.KVizIPhoneSkin",
            "font_name": "HelveticaNeue-Light",
            "wType": "Label"
        },
        "kiosk": {
            "@class": "com.kony.gen.skin.model.KVizKioskSkin",
            "background_color": "ffffffff",
            "bg_type": "one",
            "font_color": "398dcf00",
            "font_name": "GenericMonospace",
            "font_size": 170,
            "isForked": true,
            "wType": "Label"
        },
        "spaan": {
            "@class": "com.kony.gen.skin.model.KVizSPAAndroidSkin",
            "font_name": "Andale Mono",
            "wType": "Label"
        },
        "spaandroidtablet": {
            "@class": "com.kony.gen.skin.model.KVizSPAAndroidTabletSkin",
            "background_color": "ffffffff",
            "bg_type": "one",
            "bottom_left_border_color": "42424200",
            "bottom_left_border_style": "plain",
            "bottom_left_border_width": 0,
            "bottom_right_border_color": "42424200",
            "bottom_right_border_style": "plain",
            "bottom_right_border_width": 0,
            "font_color": "398dcf00",
            "font_name": "Andale Mono",
            "font_size": 170,
            "isForked": true,
            "text_shadow": {
                "br": 0,
                "color": "000000",
                "nm": 0,
                "x": 0,
                "y": 0
            },
            "top_left_border_color": "42424200",
            "top_left_border_style": "plain",
            "top_left_border_width": 0,
            "top_right_border_color": "42424200",
            "top_right_border_style": "plain",
            "top_right_border_width": 0,
            "wType": "Label"
        },
        "spabb": {
            "@class": "com.kony.gen.skin.model.KVizSPABBSkin",
            "font_name": "Andale Mono",
            "wType": "Label"
        },
        "spaip": {
            "@class": "com.kony.gen.skin.model.KVizSPAIPhoneSkin",
            "font_name": "Andale Mono",
            "wType": "Label"
        },
        "spaipad": {
            "@class": "com.kony.gen.skin.model.KVizSPAIPadSkin",
            "background_color": "ffffffff",
            "bg_type": "one",
            "bottom_left_border_color": "42424200",
            "bottom_left_border_style": "plain",
            "bottom_left_border_width": 0,
            "bottom_right_border_color": "42424200",
            "bottom_right_border_style": "plain",
            "bottom_right_border_width": 0,
            "font_color": "398dcf00",
            "font_name": "Andale Mono",
            "font_size": 170,
            "isForked": true,
            "text_shadow": {
                "br": 0,
                "color": "000000",
                "nm": 0,
                "x": 0,
                "y": 0
            },
            "top_left_border_color": "42424200",
            "top_left_border_style": "plain",
            "top_left_border_width": 0,
            "top_right_border_color": "42424200",
            "top_right_border_style": "plain",
            "top_right_border_width": 0,
            "wType": "Label"
        },
        "spawindowstablet": {
            "@class": "com.kony.gen.skin.model.KVizSPAWindowsTabletSkin",
            "background_color": "ffffffff",
            "bg_type": "one",
            "bottom_left_border_color": "42424200",
            "bottom_left_border_style": "plain",
            "bottom_left_border_width": 0,
            "bottom_right_border_color": "42424200",
            "bottom_right_border_style": "plain",
            "bottom_right_border_width": 0,
            "font_color": "398dcf00",
            "font_name": "Andale Mono",
            "font_size": 170,
            "isForked": true,
            "text_shadow": {
                "br": 0,
                "color": "000000",
                "nm": 0,
                "x": 0,
                "y": 0
            },
            "top_left_border_color": "42424200",
            "top_left_border_style": "plain",
            "top_left_border_width": 0,
            "top_right_border_color": "42424200",
            "top_right_border_style": "plain",
            "top_right_border_width": 0,
            "wType": "Label"
        },
        "spawinphone8": {
            "@class": "com.kony.gen.skin.model.KVizSPAWinPhone8Skin",
            "font_name": "Andale Mono",
            "wType": "Label"
        },
        "tabrcandroid": {
            "@class": "com.kony.gen.skin.model.KVizAndroidTabletSkin",
            "background_color": "ffffffff",
            "bg_type": "one",
            "font_color": "398dcf00",
            "font_name": "default",
            "font_size": 170,
            "isForked": true,
            "text_shadow": {
                "br": 0,
                "color": "000000",
                "nm": 0,
                "x": 0,
                "y": 0
            },
            "wType": "Label"
        },
        "windows8": {
            "@class": "com.kony.gen.skin.model.KVizWindows8Skin",
            "background_color": "ffffffff",
            "bg_type": "one",
            "font_color": "398dcf00",
            "font_name": "GenericMonospace",
            "font_size": 170,
            "isForked": true,
            "wType": "Label"
        },
        "winphone8": {
            "@class": "com.kony.gen.skin.model.KVizWinPhone8Skin",
            "font_name": "GenericMonospace",
            "wType": "Label"
        }
    },
    "shadow": {
        "br": 0,
        "color": "000000",
        "inner": false,
        "x": 0,
        "y": 0
    },
    "text_shadow": {
        "br": 0,
        "color": "000000",
        "x": 0,
        "y": 0
    },
    "top_left_border_color": "00000000",
    "top_left_border_radius": 10,
    "top_left_border_width": 0,
    "top_right_border_color": "00000000",
    "top_right_border_radius": 10,
    "top_right_border_width": 0,
    "vizChannel": "default",
    "wType": "Label"
}