{
    "@class": "com.kony.gen.skin.model.KVizSkin",
    "background_color": "ffffff00",
    "bg_type": "one",
    "border_color": "00000000",
    "border_style": "plain",
    "border_type": 0,
    "border_width": 0,
    "font_color": "00000000",
    "font_size": 100,
    "font_style": "normal",
    "font_weight": "normal",
    "isDefaultSkin": true,
    "kuid": "s01c4ca2ea33410c8966095d4253828f",
    "platforms": {
        "android": {
            "@class": "com.kony.gen.skin.model.KVizAndroidSkin",
            "background_color": "ffffff00",
            "bg_type": "one",
            "isForked": true,
            "wType": "Form"
        },
        "ipad": {
            "@class": "com.kony.gen.skin.model.KVizIPadSkin",
            "background_image": "iosfrmbgimage.png",
            "bg_type": "image",
            "isForked": true,
            "wType": "Form"
        },
        "iphone": {
            "@class": "com.kony.gen.skin.model.KVizIPhoneSkin",
            "background_image": "iosfrmbgimage.png",
            "bg_type": "image",
            "isForked": true,
            "wType": "Form"
        },
        "tabrcandroid": {
            "@class": "com.kony.gen.skin.model.KVizAndroidTabletSkin",
            "background_color": "ffffff00",
            "bg_type": "one",
            "isForked": true,
            "wType": "Form"
        }
    },
    "wType": "Form"
}